{
  "invoiceData": [
    {
      "id": "65a8",
      "invoiceHeader": {
        "date": "12/21/2024",
        "cashAmount": "54.00",
        "cardAmount": "0.00",
        "creditAmount": "0.00"
      },
      "invoiceDetails": [
        {
          "date": "12/21/2024",
          "itemdescription": "moniter",
          "itemRate": "20",
          "itemQty": "2",
          "itemDiscount": "4.00",
          "netAmount": "36.00"
        },
        {
          "date": "12/21/2024",
          "itemdescription": "mouse",
          "itemRate": "10",
          "itemQty": "2",
          "itemDiscount": "2.00",
          "netAmount": "18.00"
        }
      ]
    },
    {
      "id": "5791",
      "invoiceHeader": {
        "date": "2024-12-21",
        "cashAmount": "72.00",
        "cardAmount": "0.00",
        "creditAmount": "0.00"
      },
      "invoiceDetails": [
        {
          "itemdescription": "printer",
          "itemRate": "20",
          "itemQty": "2",
          "itemDiscount": "4.00",
          "netAmount": "36.00"
        },
        {
          "itemdescription": "speaker",
          "itemRate": "20",
          "itemQty": "2",
          "itemDiscount": "4.00",
          "netAmount": "36.00"
        }
      ]
    },
    {
      "id": "cf8c",
      "invoiceHeader": {
        "date": "2024-12-21",
        "cashAmount": "9.00",
        "cardAmount": "0.00",
        "creditAmount": "0.00"
      },
      "invoiceDetails": [
        {
          "date": "2024-12-21",
          "itemdescription": "moniter",
          "itemRate": "10",
          "itemQty": "1",
          "itemDiscount": "1.00",
          "netAmount": "9.00"
        }
      ]
    },
    {
      "id": "9736",
      "invoiceHeader": {
        "date": "2024-12-21",
        "cashAmount": "108.00",
        "cardAmount": "0.00",
        "creditAmount": "0.00"
      },
      "invoiceDetails": [
        {
          "date": "2024-12-21",
          "itemdescription": "moniter",
          "itemRate": "30",
          "itemQty": "2",
          "itemDiscount": "6.00",
          "netAmount": "54.00"
        },
        {
          "date": "2024-12-21",
          "itemdescription": "mouse",
          "itemRate": "20",
          "itemQty": "3",
          "itemDiscount": "6.00",
          "netAmount": "54.00"
        }
      ]
    }
  ]
}